COPYING
MANIFEST.in
README.md
setup.cfg
setup.py
bin/lvalert_monitor_broadcaster
bin/lvalert_monitor_listener
debian/README.Debian
debian/changelog
debian/compat
debian/control
debian/copyright
debian/rules
debian/source/format
ligo/__init__.py
ligo/lvalert_monitor/__init__.py
ligo_lvalert_monitor.egg-info/PKG-INFO
ligo_lvalert_monitor.egg-info/SOURCES.txt
ligo_lvalert_monitor.egg-info/dependency_links.txt
ligo_lvalert_monitor.egg-info/entry_points.txt
ligo_lvalert_monitor.egg-info/namespace_packages.txt
ligo_lvalert_monitor.egg-info/requires.txt
ligo_lvalert_monitor.egg-info/top_level.txt